python_custom_logging/__init__.py
python_custom_logging/python_custom_logging.py
python_custom_logging-1.0.1.dist-info/METADATA
python_custom_logging-1.0.1.dist-info/WHEEL
python_custom_logging-1.0.1.dist-info/top_level.txt
python_custom_logging-1.0.1.dist-info/RECORD
