Metadata-Version: 2.1
Name: python-custom-logging
Version: 1.0.1
Summary: Package to create log files with using TimedRotatingFileHandler
Author: Pankaj Kalal
Author-email: pankajgkalal@gmail.com
License: UNKNOWN
Platform: UNKNOWN
Classifier: Programming Language :: Python :: 3
Classifier: License :: OSI Approved :: MIT License
Classifier: Operating System :: OS Independent
Requires-Python: >=3.7
